traini_ai/__init__.py
traini_ai/client.py
traini_ai/models/__init__.py
traini_ai/models/classes.json
traini_ai/models/emotion_model.py
traini_ai/models/ensemble_emotion_model.py
traini_ai/modules/__init__.py
traini_ai/modules/base.py
traini_ai/modules/dog_to_human.py
traini_ai/modules/human_to_dog.py
traini_ai/modules/image_analyzer.py
traini_ai/modules/image_analyzer_ensemble.py
traini_ai/modules/integrated_analysis_with_emotion.py
traini_ai/modules/video_analyzer.py
traini_ai/utils/__init__.py
traini_ai/utils/config.py
traini_ai/utils/exceptions.py
traini_ai/utils/validators.py
traini_ai-2.0.9.dist-info/licenses/LICENSE
traini_ai-2.0.9.dist-info/METADATA
traini_ai-2.0.9.dist-info/WHEEL
traini_ai-2.0.9.dist-info/top_level.txt
traini_ai-2.0.9.dist-info/RECORD
