Metadata-Version: 2.4
Name: traini-ai
Version: 2.0.9
Summary: Traini AI SDK - Dog emotion analysis and human-dog communication platform
Home-page: https://github.com/Traini-Inc/traini-sdk
Author: Traini AI Team
Author-email: Traini AI Team <support@traini.ai>
License: MIT
Project-URL: Homepage, https://github.com/Traini-Inc/traini-sdk
Project-URL: Documentation, https://github.com/Traini-Inc/traini-sdk
Project-URL: Repository, https://github.com/Traini-Inc/traini-sdk
Project-URL: Bug Tracker, https://github.com/Traini-Inc/traini-sdk/issues
Keywords: traini,ai,dog,emotion,analysis,translation,audio,video,machine-learning,pet
Classifier: Development Status :: 4 - Beta
Classifier: Intended Audience :: Developers
Classifier: Intended Audience :: Science/Research
Classifier: Topic :: Scientific/Engineering :: Artificial Intelligence
Classifier: Topic :: Multimedia :: Sound/Audio :: Analysis
Classifier: License :: OSI Approved :: MIT License
Classifier: Programming Language :: Python :: 3
Classifier: Programming Language :: Python :: 3.8
Classifier: Programming Language :: Python :: 3.9
Classifier: Programming Language :: Python :: 3.10
Classifier: Programming Language :: Python :: 3.11
Requires-Python: >=3.8
License-File: LICENSE
Requires-Dist: numpy>=1.21.0
Requires-Dist: pillow>=9.0.0
Requires-Dist: requests>=2.27.0
Requires-Dist: torch>=1.12.0
Requires-Dist: torchvision>=0.13.0
Requires-Dist: openai>=1.0.0
Requires-Dist: google-generativeai>=0.3.0
Requires-Dist: anthropic>=0.8.0
Requires-Dist: huggingface_hub>=0.20.0
Provides-Extra: dev
Requires-Dist: pytest>=7.0.0; extra == "dev"
Requires-Dist: pytest-cov>=3.0.0; extra == "dev"
Requires-Dist: black>=22.0.0; extra == "dev"
Requires-Dist: flake8>=4.0.0; extra == "dev"
Requires-Dist: mypy>=0.950; extra == "dev"
Provides-Extra: ml
Requires-Dist: torch>=1.12.0; extra == "ml"
Requires-Dist: torchvision>=0.13.0; extra == "ml"
Requires-Dist: opencv-python>=4.6.0; extra == "ml"
Provides-Extra: audio
Requires-Dist: librosa>=0.9.0; extra == "audio"
Requires-Dist: soundfile>=0.11.0; extra == "audio"
Requires-Dist: pydub>=0.25.0; extra == "audio"
Provides-Extra: all
Requires-Dist: torch>=1.12.0; extra == "all"
Requires-Dist: torchvision>=0.13.0; extra == "all"
Requires-Dist: opencv-python>=4.6.0; extra == "all"
Requires-Dist: librosa>=0.9.0; extra == "all"
Requires-Dist: soundfile>=0.11.0; extra == "all"
Requires-Dist: pydub>=0.25.0; extra == "all"
Dynamic: author
Dynamic: home-page
Dynamic: license-file
Dynamic: requires-python
